{
  "title": "Trading Dashboard",
  "description": "Crypto monitoring dashboard",
  "theme": "dark",
    "groups": [
    "BossaG",
    "BossaE",
    "XTB",
    "Binnance",
    "ETFs",
    "Stocks"
  ],
  "widgets": [
    {
      "title": "ServiceNow, Inc.",
      "symbol": "NYSE:NOW",
      "tvSymbolUrl": "NYSE-NOW",
      "interval": "60",
      "height": 500,
      "groups": ["XTB","Stocks"]
    },
    {
      "title": "Meta Platforms Inc Class A",
      "symbol": "NASDAQ:META",
      "tvSymbolUrl": "NASDAQ-META",
      "interval": "60",
      "height": 500,
       "groups": ["XTB","Stocks"]
    },
    {
      "title": "Tesla, Inc.",
      "symbol": "NASDAQ:TSLA",
      "tvSymbolUrl": "NASDAQ-TSLA",
      "interval": "60",
      "height": 500,
      "groups": ["XTB","Stocks"]
    },
    {
      "title": "Lam Research Corporation",
      "symbol": "NASDAQ:LRCX",
      "tvSymbolUrl": "NASDAQ-LRCX",
      "interval": "60",
      "height": 500,
      "groups": ["XTB","Stocks"]
    },
    {
      "title": "iShares S&P 500 Information Technology Sector UCITS ETF",
      "symbol": "LSE:IUIT",
      "tvSymbolUrl": "LSE-IUIT",
      "interval": "60",
      "height": 500,
      "groups": ["XTB","ETFs"]
    }
    
  ]
}
